{
  "kind": "collectionType",
  "collectionName": "works",
  "info": {
    "name": "work",
    "description": ""
  },
  "options": {
    "increments": true,
    "timestamps": true,
    "draftAndPublish": true
  },
  "pluginOptions": {},
  "attributes": {
    "name": {
      "type": "string"
    },
    "image": {
      "model": "file",
      "via": "related",
      "allowedTypes": [
        "images",
        "files",
        "videos"
      ],
      "plugin": "upload",
      "required": false,
      "pluginOptions": {}
    },
    "content": {
      "type": "richtext"
    },
    "thumb": {
      "model": "file",
      "via": "related",
      "allowedTypes": [
        "images",
        "files",
        "videos"
      ],
      "plugin": "upload",
      "required": false,
      "pluginOptions": {}
    },
    "skills": {
      "collection": "skills",
      "via": "works",
      "dominant": true
    },
    "slug": {
      "type": "string"
    },
    "subtitle": {
      "type": "string"
    },
    "priority": {
      "type": "integer"
    }
  }
}
